AUTHORS
LICENSE
MANIFEST.in
README.md
setup.py
sortable/__init__.py
sortable/admin.py
sortable/models.py
sortable.egg-info/PKG-INFO
sortable.egg-info/SOURCES.txt
sortable.egg-info/dependency_links.txt
sortable.egg-info/not-zip-safe
sortable.egg-info/top_level.txt