Metadata-Version: 1.0
Name: sortable
Version: 0.1
Summary: An app to add drag-and-drop to Grappelli admin to reorder instances of models.
Home-page: http://github.com/ff0000/sortable/
Author: Red Interactive Agency
Author-email: geeks@ff0000.com
License: UNKNOWN
Platform: UNKNOWN
Classifier: Development Status :: 2 - Pre-Alpha
Classifier: Environment :: Web Environment
Classifier: Intended Audience :: Developers
Classifier: License :: OSI Approved :: BSD License
Classifier: Operating System :: OS Independent
Classifier: Programming Language :: Python
Classifier: Framework :: Django
